suclepy/__init__.py
suclepy/main.py
suclepy/cli/__init__.py
suclepy/cli/suclepy_cli.py
suclepy/config/__init__.py
suclepy/config/settings.py
suclepy/core/__init__.py
suclepy/core/analyzer.py
suclepy/core/cleaner.py
suclepy/core/reporter.py
suclepy/core/role_infer.py
suclepy/core/utils.py
suclepy/core/validator.py
suclepy/tests/__init__.py
suclepy/tests/test_all.py
suclepy-1.0.1.dist-info/licenses/LICENSE
suclepy-1.0.1.dist-info/METADATA
suclepy-1.0.1.dist-info/WHEEL
suclepy-1.0.1.dist-info/top_level.txt
suclepy-1.0.1.dist-info/RECORD
