Metadata-Version: 2.4
Name: suclepy
Version: 1.0.1
Summary: SUCLEPY — Smart Universal Cleaner Library for Python
Home-page: https://github.com/subodhkryadav/suclepy
Author: Subodh Kumar Yadav
Author-email: Subodh Kumar Yadav <subodhkumary933@gmail.com>
License: MIT
Project-URL: Homepage, https://github.com/subodhkryadav/suclepy
Project-URL: Source, https://github.com/subodhkryadav/suclepy
Project-URL: Tracker, https://github.com/subodhkryadav/suclepy/issues
Keywords: data-cleaning,data-validation,data-analysis,python
Classifier: Programming Language :: Python :: 3
Classifier: License :: OSI Approved :: MIT License
Classifier: Operating System :: OS Independent
Requires-Python: >=3.8
License-File: LICENSE
Requires-Dist: pandas>=2.0
Requires-Dist: numpy>=1.25
Requires-Dist: tabulate>=0.9
Dynamic: author
Dynamic: home-page
Dynamic: license-file
Dynamic: requires-python
